Metadata-Version: 2.1
Name: DA-DAPPER
Version: 1.2.2
Summary: DAPPER benchmarks the performance of data assimilation (DA) methods.
Home-page: UNKNOWN
Author: Patrick N. Raanes
Author-email: patrick.n.raanes@gmail.com
License: UNKNOWN
Project-URL: Documentation, https://nansencenter.github.io/DAPPER/
Project-URL: Source, https://github.com/nansencenter/DAPPER
Project-URL: Tracker, https://github.com/nansencenter/DAPPER/issues
Keywords: data-assimilation enkf kalman-filtering state-estimation particle-filter kalman bayesian-methods bayesian-filter chaos
Platform: UNKNOWN
Classifier: Development Status :: 3 - Alpha
Classifier: Intended Audience :: Science/Research
Classifier: Topic :: Scientific/Engineering :: Mathematics
Classifier: Programming Language :: Python :: 3
Classifier: License :: OSI Approved :: MIT License
Classifier: Operating System :: OS Independent
Requires-Python: >=3.7
Requires-Dist: scipy (>=1.1)
Requires-Dist: ipython (>=5.1)
Requires-Dist: jedi (<0.18)
Requires-Dist: jupyter
Requires-Dist: matplotlib (~=3.2.2)
Requires-Dist: mpl-tools (==0.2.36)
Requires-Dist: tqdm (~=4.31)
Requires-Dist: pyyaml
Requires-Dist: ipdb
Requires-Dist: colorama (~=0.4.1)
Requires-Dist: tabulate (~=0.8.3)
Requires-Dist: dill (==0.3.2)
Requires-Dist: patlib (==0.3.5)
Requires-Dist: struct-tools (==0.2.5)
Requires-Dist: multiprocessing-on-dill (==3.5.0a4)
Requires-Dist: threadpoolctl (==1.0.0)
Provides-Extra: qt
Requires-Dist: PyQt5 ; extra == 'qt'
Requires-Dist: qtpy ; extra == 'qt'
Provides-Extra: build
Requires-Dist: twine ; extra == 'build'
Requires-Dist: pdoc3 ; extra == 'build'
Requires-Dist: jupytext ; extra == 'build'
Provides-Extra: dev
Requires-Dist: line-profiler ; extra == 'dev'
Requires-Dist: pre-commit ; extra == 'dev'
Requires-Dist: tox ; extra == 'dev'
Requires-Dist: coverage ; extra == 'dev'
Requires-Dist: pytest ; extra == 'dev'
Requires-Dist: pytest-cov ; extra == 'dev'
Requires-Dist: pytest-sugar ; extra == 'dev'
Requires-Dist: pytest-benchmark ; extra == 'dev'
Requires-Dist: pytest-clarity ; extra == 'dev'
Requires-Dist: pytest-xdist ; extra == 'dev'
Requires-Dist: pytest-timeout ; extra == 'dev'
Requires-Dist: flake8 ; extra == 'dev'
Requires-Dist: flakehell ; extra == 'dev'
Requires-Dist: twine ; extra == 'dev'
Requires-Dist: pdoc3 ; extra == 'dev'
Requires-Dist: jupytext ; extra == 'dev'
Provides-Extra: lint
Requires-Dist: flake8 ; extra == 'lint'
Requires-Dist: flakehell ; extra == 'lint'
Provides-Extra: test
Requires-Dist: tox ; extra == 'test'
Requires-Dist: coverage ; extra == 'test'
Requires-Dist: pytest ; extra == 'test'
Requires-Dist: pytest-cov ; extra == 'test'
Requires-Dist: pytest-sugar ; extra == 'test'
Requires-Dist: pytest-benchmark ; extra == 'test'
Requires-Dist: pytest-clarity ; extra == 'test'
Requires-Dist: pytest-xdist ; extra == 'test'
Requires-Dist: pytest-timeout ; extra == 'test'
